{
  "version": "1.0",
  "total": 25,
  "fueros": [
    {
      "fuero": "laboral",
      "fuero_label": "Laboral",
      "descripcion": "Juzgado de Conciliación / Cámara del Trabajo",
      "demos": [
        {
          "id": "laboral_01",
          "file": "laboral_01.json",
          "titulo": "Admisión de demanda laboral",
          "proceso": "Juicio Ordinario Laboral",
          "etapa": "Admisión y citación a audiencia",
          "tipo": "admision_laboral"
        },
        {
          "id": "laboral_02",
          "file": "laboral_02.json",
          "titulo": "Auto de apertura a prueba",
          "proceso": "Juicio Ordinario Laboral",
          "etapa": "Apertura del período probatorio",
          "tipo": "auto_apertura_laboral"
        },
        {
          "id": "laboral_03",
          "file": "laboral_03.json",
          "titulo": "Homologación de acuerdo laboral",
          "proceso": "Juicio Ordinario Laboral",
          "etapa": "Homologación del acuerdo conciliatorio",
          "tipo": "homologacion_acuerdo_laboral"
        },
        {
          "id": "laboral_04",
          "file": "laboral_04.json",
          "titulo": "Citación a vista de causa",
          "proceso": "Juicio Ordinario Laboral",
          "etapa": "Vista de causa",
          "tipo": "citacion_vista_causa"
        },
        {
          "id": "laboral_05",
          "file": "laboral_05.json",
          "titulo": "Intimación de pago de liquidación",
          "proceso": "Juicio Ordinario Laboral",
          "etapa": "Ejecución de sentencia",
          "tipo": "intimacion_pago_liquidacion"
        }
      ]
    },
    {
      "fuero": "civil_comercial",
      "fuero_label": "Civil y Comercial",
      "descripcion": "Juzgado Civil y Comercial",
      "demos": [
        {
          "id": "civil_01",
          "file": "civil_01.json",
          "titulo": "Traslado de demanda ordinaria",
          "proceso": "Juicio Ordinario Civil",
          "etapa": "Traslado de demanda",
          "tipo": "traslado_demanda"
        },
        {
          "id": "civil_02",
          "file": "civil_02.json",
          "titulo": "Embargo preventivo",
          "proceso": "Medida Cautelar",
          "etapa": "Embargo preventivo",
          "tipo": "embargo_preventivo"
        },
        {
          "id": "civil_03",
          "file": "civil_03.json",
          "titulo": "Intimación de pago (ejecutivo)",
          "proceso": "Juicio Ejecutivo",
          "etapa": "Intimación de pago",
          "tipo": "intimacion_pago"
        },
        {
          "id": "civil_04",
          "file": "civil_04.json",
          "titulo": "Apertura a prueba (ordinario)",
          "proceso": "Juicio Ordinario Civil",
          "etapa": "Apertura del período probatorio",
          "tipo": "auto_apertura_ordinario"
        },
        {
          "id": "civil_05",
          "file": "civil_05.json",
          "titulo": "Declaratoria de herederos",
          "proceso": "Sucesión",
          "etapa": "Declaratoria de herederos",
          "tipo": "declaratoria_herederos"
        }
      ]
    },
    {
      "fuero": "familia",
      "fuero_label": "Familia",
      "descripcion": "Juzgado de Familia",
      "demos": [
        {
          "id": "familia_01",
          "file": "familia_01.json",
          "titulo": "Alimentos provisorios",
          "proceso": "Alimentos",
          "etapa": "Alimentos provisorios",
          "tipo": "alimentos_provisorios"
        },
        {
          "id": "familia_02",
          "file": "familia_02.json",
          "titulo": "Admisión de divorcio bilateral",
          "proceso": "Divorcio Vincular",
          "etapa": "Admisión de la petición",
          "tipo": "admision_divorcio"
        },
        {
          "id": "familia_03",
          "file": "familia_03.json",
          "titulo": "Exclusión del hogar",
          "proceso": "Exclusión del Hogar / Atribución",
          "etapa": "Exclusión del hogar",
          "tipo": "exclusion_hogar"
        },
        {
          "id": "familia_04",
          "file": "familia_04.json",
          "titulo": "Régimen de comunicación provisorio",
          "proceso": "Régimen de Comunicación",
          "etapa": "Régimen provisorio",
          "tipo": "regimen_comunicacion_provisorio"
        },
        {
          "id": "familia_05",
          "file": "familia_05.json",
          "titulo": "Homologación de convenio regulador",
          "proceso": "Divorcio Vincular",
          "etapa": "Homologación del convenio regulador",
          "tipo": "homologacion_acuerdo_familia"
        }
      ]
    },
    {
      "fuero": "penal",
      "fuero_label": "Penal",
      "descripcion": "Juzgado de Control / Juzgado Correccional",
      "demos": [
        {
          "id": "penal_01",
          "file": "penal_01.json",
          "titulo": "Citación al acto de imputación",
          "proceso": "Investigación Penal Preparatoria",
          "etapa": "Acto de imputación",
          "tipo": "citacion_imputacion"
        },
        {
          "id": "penal_02",
          "file": "penal_02.json",
          "titulo": "Auto de prisión preventiva",
          "proceso": "Investigación Penal Preparatoria",
          "etapa": "Medida cautelar personal",
          "tipo": "prision_preventiva"
        },
        {
          "id": "penal_03",
          "file": "penal_03.json",
          "titulo": "Sobreseimiento por falta de prueba",
          "proceso": "Investigación Penal Preparatoria",
          "etapa": "Sobreseimiento definitivo",
          "tipo": "sobreseimiento"
        },
        {
          "id": "penal_04",
          "file": "penal_04.json",
          "titulo": "Auto de elevación a juicio oral",
          "proceso": "Investigación Penal Preparatoria",
          "etapa": "Elevación a juicio",
          "tipo": "auto_elevacion_juicio"
        },
        {
          "id": "penal_05",
          "file": "penal_05.json",
          "titulo": "Suspensión del juicio a prueba",
          "proceso": "Juicio",
          "etapa": "Suspensión del juicio a prueba",
          "tipo": "suspension_juicio_prueba"
        }
      ]
    },
    {
      "fuero": "contencioso_administrativo",
      "fuero_label": "Contencioso Administrativo",
      "descripcion": "Cámara Contencioso Administrativa",
      "demos": [
        {
          "id": "ca_01",
          "file": "ca_01.json",
          "titulo": "Admisibilidad de acción contencioso-administrativa",
          "proceso": "Acción Contencioso Administrativa",
          "etapa": "Admisibilidad formal",
          "tipo": "admisibilidad_ca"
        },
        {
          "id": "ca_02",
          "file": "ca_02.json",
          "titulo": "Traslado de demanda contencioso-administrativa",
          "proceso": "Acción Contencioso Administrativa",
          "etapa": "Traslado de demanda",
          "tipo": "traslado_demanda_ca"
        },
        {
          "id": "ca_03",
          "file": "ca_03.json",
          "titulo": "Suspensión cautelar del acto administrativo",
          "proceso": "Acción Contencioso Administrativa",
          "etapa": "Medida cautelar",
          "tipo": "suspension_acto_administrativo"
        },
        {
          "id": "ca_04",
          "file": "ca_04.json",
          "titulo": "Citación a audiencia preliminar",
          "proceso": "Acción Contencioso Administrativa",
          "etapa": "Audiencia preliminar",
          "tipo": "citacion_audiencia_preliminar_ca"
        },
        {
          "id": "ca_05",
          "file": "ca_05.json",
          "titulo": "Llamamiento de autos para sentencia",
          "proceso": "Acción Contencioso Administrativa",
          "etapa": "Llamamiento de autos",
          "tipo": "llamamiento_autos_ca"
        }
      ]
    }
  ]
}
